Metadata-Version: 1.0
Name: stats-distro
Version: 0.1
Summary: Binomial and Gaussian distributions and some functionalitites
Home-page: UNKNOWN
Author: Kunal Sharma
Author-email: kushkunal077@gmail.com
License: UNKNOWN
Platform: UNKNOWN
